VectorTileGenerator/__init__.py
VectorTileGenerator/generator.py
VectorTileGenerator-0.0.6.dist-info/METADATA
VectorTileGenerator-0.0.6.dist-info/WHEEL
VectorTileGenerator-0.0.6.dist-info/entry_points.txt
VectorTileGenerator-0.0.6.dist-info/top_level.txt
VectorTileGenerator-0.0.6.dist-info/RECORD
