Metadata-Version: 2.1
Name: VectorTileGenerator
Version: 0.0.6
Summary: Automatically generate a list of all possible tiles options between two zoom levels and a bounding box.
Home-page: https://github.com/mkeller3/VectorTileGenerator/
Author: Michael Keller
Author-email: michaelkeller03@gmail.com
License: GNU General Public License v3.0
Platform: UNKNOWN
Classifier: License :: OSI Approved :: GNU General Public License v3 (GPLv3)
Classifier: Programming Language :: Python :: 3
Classifier: Programming Language :: Python :: 3.7
Requires-Dist: geojson (==2.5.0)
Requires-Dist: joblib (==1.1.0)
Requires-Dist: turfpy (==0.0.7)
